fw_gear_ants_buildtemplateparallel/__init__.py
fw_gear_ants_buildtemplateparallel/interfaces.py
fw_gear_ants_buildtemplateparallel/parser.py
fw_gear_ants_buildtemplateparallel/templates/MNI152_T1_1mm.nii.gz
fw_gear_ants_buildtemplateparallel/utils.py
fw_gear_ants_buildtemplateparallel/workflow.py
fw_gear_ants_buildtemplateparallel-0.1.0.dist-info/LICENSE
fw_gear_ants_buildtemplateparallel-0.1.0.dist-info/WHEEL
fw_gear_ants_buildtemplateparallel-0.1.0.dist-info/METADATA
fw_gear_ants_buildtemplateparallel-0.1.0.dist-info/RECORD
