Metadata-Version: 2.1
Name: fw-gear-ants-buildtemplateparallel
Version: 0.1.0
Summary: Run ANTs buildtemplateparallel.sh script and generate templates.
Home-page: https://gitlab.com/flywheel-io/flywheel-apps/ants-buildtemplateparallel
License: MIT
Keywords: Flywheel,Gears
Author: Flywheel
Author-email: support@flywheel.io
Requires-Python: >=3.8,<4.0
Classifier: License :: OSI Approved :: MIT License
Classifier: Programming Language :: Python :: 3
Classifier: Programming Language :: Python :: 3.8
Classifier: Programming Language :: Python :: 3.9
Classifier: Topic :: Scientific/Engineering
Requires-Dist: backoff (>=1.11.1,<2.0.0)
Requires-Dist: flywheel-gear-toolkit (>=0.3,<0.4)
Requires-Dist: joblib (>=1.0.1,<2.0.0)
Requires-Dist: nipype (>=1.6.1,<2.0.0)
Project-URL: Repository, https://gitlab.com/flywheel-io/flywheel-apps/ants-buildtemplateparallel
